ebhkit/__init__.py
ebhkit/_version.py
ebhkit/file/__init__.py
ebhkit/file/read_json_file.py
ebhkit/file/read_text_file.py
ebhkit/file/save_dict_to_file.py
ebhkit-0.2.1.dev0.dist-info/licenses/LICENSE
ebhkit-0.2.1.dev0.dist-info/METADATA
ebhkit-0.2.1.dev0.dist-info/WHEEL
ebhkit-0.2.1.dev0.dist-info/top_level.txt
ebhkit-0.2.1.dev0.dist-info/RECORD
