Metadata-Version: 2.4
Name: ebhkit
Version: 0.2.1.dev0
Summary: A tiny collection of reusable helper utilities.
Author-email: Ehsan Bitaraf <ehsan.bitaraf@gmail.com>
License: MIT License
Project-URL: Homepage, https://github.com/yourname/myhelpers
Project-URL: Issues, https://github.com/yourname/myhelpers/issues
Keywords: helpers,utilities,toolkit
Classifier: Programming Language :: Python :: 3
Classifier: Programming Language :: Python :: 3 :: Only
Classifier: Programming Language :: Python :: 3.9
Classifier: License :: OSI Approved :: MIT License
Classifier: Operating System :: OS Independent
Requires-Python: >=3.9
License-File: LICENSE
Dynamic: license-file
